AUTHORS.txt
LICENSE.txt
MANIFEST.in
README.rst
setup.py
pyqode/__init__.py
pyqode/designer.py
pyqode.designer.egg-info/PKG-INFO
pyqode.designer.egg-info/SOURCES.txt
pyqode.designer.egg-info/dependency_links.txt
pyqode.designer.egg-info/entry_points.txt
pyqode.designer.egg-info/namespace_packages.txt
pyqode.designer.egg-info/requires.txt
pyqode.designer.egg-info/top_level.txt