Metadata-Version: 1.1
Name: pyqode.designer
Version: 1.2
Summary: Starts Qt Designer with pyqode plugins
Home-page: https://github.com/pyQode/pyqode.designer
Author: Colin Duquesnoy
Author-email: colin.duquesnoy@gmail.com
License: MIT
Keywords: QCodeEditor,PySide,PyQt,designer,Qt
Platform: UNKNOWN
Classifier: Development Status :: 5 - Production/Stable
Classifier: Environment :: X11 Applications :: Qt
Classifier: Environment :: Win32 (MS Windows)
Classifier: Intended Audience :: Developers
Classifier: License :: OSI Approved :: MIT License
Classifier: Operating System :: Microsoft :: Windows
Classifier: Operating System :: POSIX :: Linux
Classifier: Programming Language :: Python :: 2.7
Classifier: Programming Language :: Python :: 3.2
Classifier: Programming Language :: Python :: 3.3
